monedadigitag/__init__.py
monedadigitalg/__init__.py
monedadigitalg-4.0.0.dist-info/METADATA
monedadigitalg-4.0.0.dist-info/WHEEL
monedadigitalg-4.0.0.dist-info/top_level.txt
monedadigitalg-4.0.0.dist-info/RECORD
